ner_entity_annotator/__init__.py
ner_entity_annotator/example.py
ner_entity_annotator/frontend/build/asset-manifest.json
ner_entity_annotator/frontend/build/bootstrap.min.css
ner_entity_annotator/frontend/build/index.html
ner_entity_annotator/frontend/build/static/js/main.107f32a5.js
ner_entity_annotator/frontend/build/static/js/main.107f32a5.js.LICENSE.txt
ner_entity_annotator/frontend/build/static/js/main.107f32a5.js.map
ner_entity_annotator/frontend/build/static/js/main.e2b65f40.js
ner_entity_annotator/frontend/build/static/js/main.e2b65f40.js.LICENSE.txt
ner_entity_annotator/frontend/build/static/js/main.e2b65f40.js.map
ner_entity_annotator-0.0.5.dist-info/LICENSE
ner_entity_annotator-0.0.5.dist-info/METADATA
ner_entity_annotator-0.0.5.dist-info/WHEEL
ner_entity_annotator-0.0.5.dist-info/top_level.txt
ner_entity_annotator-0.0.5.dist-info/RECORD
