Metadata-Version: 2.1
Name: ner-entity-annotator
Version: 0.0.5
Summary: Streamlit component that allows you to visualize and modify NER annotations
Home-page: 
Author: Dmitry Yemelyanov
Author-email: dmitry@forwardit.ai
Requires-Python: >=3.7
License-File: LICENSE
Requires-Dist: streamlit>=0.63
Provides-Extra: devel
Requires-Dist: wheel; extra == "devel"
Requires-Dist: pytest==7.4.0; extra == "devel"
Requires-Dist: playwright==1.48.0; extra == "devel"
Requires-Dist: requests==2.31.0; extra == "devel"
Requires-Dist: pytest-playwright-snapshot==1.0; extra == "devel"
Requires-Dist: pytest-rerunfailures==12.0; extra == "devel"
